Workbook

Sheet Assumptions
A1: DCF VALUATION MODEL | ASSUMPTIONS SHEET
A4: COMPANY INFORMATION
A5: Company Name | B5: Natco Pharma Ltd
A6: Stock Exchange | B6: NSE / BSE
A7: Ticker Symbol | B7: NATCOPHARM
A8: Currency | B8: INR
A9: Units | B9: ₹ Crores
A10: Valuation Date | B10: 46169
A11: Analyst Name | B11: Lakshay Gupta
A13: HISTORICAL FINANCIALS (₹ Crores) — source: Screener.in / Annual Reports
A14: Line Item | B14: FY2021 | C14: FY2022 | D14: FY2023 | E14: FY2024 | F14: FY2025
A15: Revenue | B15: 2052 | C15: 1945 | D15: 2707 | E15: 3999 | F15: 4430
A16: EBITDA | B16: 606 | C16: 264 | D16: 936 | E16: 1754 | F16: 2196
A17: EBIT (Operating Profit) | B17: 489 | C17: 121 | D17: 772 | E17: 1567 | F17: 1961
A18: Depreciation & Amortisation | B18: 117 | C18: 143 | D18: 164 | E18: 187 | F18: 235
A19: Net Profit (PAT) | B19: 442 | C19: 170 | D19: 715 | E19: 1388 | F19: 1883
A20: Capital Expenditure (Capex) | B20: 207 | C20: 188 | D20: 175 | E20: 357 | F20: 397
A21: Change in Working Capital | B21: 200 | C21: 300 | D21: 80 | E21: 180 | F21: 150
A22: Tax Rate (%) | B22: 0.24 | C22: 0.16 | D22: 0.17 | E22: 0.17 | F22: 0.18
A23: Shares Outstanding (Crores) | B23: 17.89 | C23: 17.89 | D23: 17.89 | E23: 17.89 | F23: 17.89
A25: PROJECTION ASSUMPTIONS (Change cells in YELLOW)
A26: Assumption | B26: FY2026E | C26: FY2027E | D26: FY2028E | E26: FY2029E | F26: FY2030E
A27: Revenue Growth Rate (%) | B27: -0.1 | C27: -0.08 | D27: 0.1 | E27: 0.12 | F27: 0.12
A28: EBITDA Margin (%) | B28: 0.3 | C28: 0.28 | D28: 0.3 | E28: 0.32 | F28: 0.34
A29: D&A as % of Revenue (%) | B29: 0.055 | C29: 0.06 | D29: 0.058 | E29: 0.055 | F29: 0.055
A30: Capex as % of Revenue (%) | B30: 0.09 | C30: 0.095 | D30: 0.085 | E30: 0.08 | F30: 0.075
A31: ΔWorking Capital (₹ Cr) | B31: 100 | C31: 80 | D31: 120 | E31: 130 | F31: 140
A32: Tax Rate (%) | B32: 0.18 | C32: 0.18 | D32: 0.19 | E32: 0.2 | F32: 0.2
A35: Risk-Free Rate (10-yr Gsec %) | B35: 0.071
A36: Equity Risk Premium (%) | B36: 0.055
A37: Beta (levered) | B37: 0.75
A38: Cost of Equity (%) | B38: =B35+B37*B36 -> 0.11225
A39: Pre-Tax Cost of Debt (%) | B39: 0.085
A40: Tax Rate for WACC (%) | B40: 0.18
A41: After-Tax Cost of Debt (%) | B41: =B39*(1-B40) -> 0.0697
A42: Equity Weight (%) | B42: 0.96
A43: Debt Weight (%) | B43: =1-B42 -> 0.04
A44: WACC (%) | B44: =B38*B42+B41*B43 -> 0.110548
A46: Terminal growth rate assumption
A47: Terminal growth rate | B47: 0.05

Sheet DCF Model
A1: DCF VALUATION MODEL | FREE CASH FLOW & VALUATION
A2: All figures in ₹ Crores unless stated. Formulas pull from Assumptions sheet.
B3: FY2026E | C3: FY2027E | D3: FY2028E | E3: FY2029E | F3: FY2030E
A4: FREE CASH FLOW BUILD-UP (₹ Crores)
A5: Revenue | B5: =Assumptions!F15*(1+Assumptions!B27) -> 3987 | C5: =B5*(1+Assumptions!C27) -> 3668.04 | D5: =C5*(1+Assumptions!D27) -> 4034.844 | E5: =D5*(1+Assumptions!E27) -> 4519.0253 | F5: =E5*(1+Assumptions!F27) -> 5061.3083
A6: EBITDA | B6: =B5*Assumptions!B28 -> 1196.1 | C6: =C5*Assumptions!C28 -> 1027.0512 | D6: =D5*Assumptions!D28 -> 1210.4532 | E6: =E5*Assumptions!E28 -> 1446.0881 | F6: =F5*Assumptions!F28 -> 1720.8448
A7: Depreciation & Amortisation | B7: =B5*Assumptions!B29 -> 219.285 | C7: =C5*Assumptions!C29 -> 220.0824 | D7: =D5*Assumptions!D29 -> 234.02095 | E7: =E5*Assumptions!E29 -> 248.54639 | F7: =F5*Assumptions!F29 -> 278.37196
A8: EBIT (Operating Profit) | B8: =B6-B7 -> 976.815 | C8: =C6-C7 -> 806.9688 | D8: =D6-D7 -> 976.43225 | E8: =E6-E7 -> 1197.5417 | F8: =F6-F7 -> 1442.4729
A9: NOPAT [EBIT × (1 – Tax Rate)] | B9: =B8*(1-Assumptions!B32) -> 800.9883 | C9: =C8*(1-Assumptions!C32) -> 661.71442 | D9: =D8*(1-Assumptions!D32) -> 790.91012 | E9: =E8*(1-Assumptions!E32) -> 958.03336 | F9: =F8*(1-Assumptions!F32) -> 1153.9783
A10: Add: Depreciation & Amortisation | B10: =B7 -> 219.285 | C10: =C7 -> 220.0824 | D10: =D7 -> 234.02095 | E10: =E7 -> 248.54639 | F10: =F7 -> 278.37196
A11: Less: Capital Expenditure (Capex) | B11: =B5*Assumptions!B30 -> 358.83 | C11: =C5*Assumptions!C30 -> 348.4638 | D11: =D5*Assumptions!D30 -> 342.96174 | E11: =E5*Assumptions!E30 -> 361.52202 | F11: =F5*Assumptions!F30 -> 379.59812
A12: Less: Change in Working Capital (ΔWC) | B12: =Assumptions!B31 -> 100 | C12: =Assumptions!C31 -> 80 | D12: =Assumptions!D31 -> 120 | E12: =Assumptions!E31 -> 130 | F12: =Assumptions!F31 -> 140
A13: FREE CASH FLOW TO FIRM (FCFF) | B13: =B9+B10-B11-B12 -> 561.4433 | C13: =C9+C10-C11-C12 -> 453.33302 | D13: =D9+D10-D11-D12 -> 561.96933 | E13: =E9+E10-E11-E12 -> 715.05773 | F13: =F9+F10-F11-F12 -> 912.75213
A15: DISCOUNTING (WACC pulled from Assumptions)
A16: Discount Period (Year) | B16: 1 | C16: 2 | D16: 3 | E16: 4 | F16: 5
A17: Discount Factor [1/(1+WACC)^t] | B17: =1/(1+Assumptions!B44)^B16 -> 0.90045635 | C17: =1/(1+Assumptions!B44)^C16 -> 0.81082164 | D17: =1/(1+Assumptions!B44)^D16 -> 0.7301095 | E17: =1/(1+Assumptions!B44)^E16 -> 0.65743173 | F17: =1/(1+Assumptions!B44)^F16 -> 0.59198858
A18: PV of FCFF | B18: =B13*B17 -> 505.55519 | C18: =C13*C17 -> 367.57222 | D18: =D13*D17 -> 410.29915 | E18: =E13*E17 -> 470.10164 | F18: =F13*F17 -> 540.33884
A20: TERMINAL VALUE (Gordon Growth Model)
A21: Terminal Value [FCF5 × (1+g) / (WACC – g)] | B21: =F13*(1+Assumptions!B47)/(Assumptions!B44-Assumptions!B47) -> 15828.594
A22: PV of Terminal Value | B22: =B21*F17 -> 9370.3471
A24: VALUATION SUMMARY (₹ Crores)
A25: Sum of PV of FCFFs | B25: =SUM(B18:F18) -> 2293.867
A26: Enterprise Value (EV) | B26: =B25+B22 -> 11664.214
A27: Less: Total Debt (₹ Cr) | B27: 279
A28: Add: Cash & Equivalents (₹ Cr) | B28: 3500
A29: Equity Value | B29: =B26-B27+B28 -> 14885.214
A30: Shares Outstanding (Crores) | B30: =Assumptions!F23 -> 17.89
A31: Intrinsic Value per Share (₹) | B31: =IFERROR(B29/B30,0) -> 832.04104
A33: Current Market Price (₹) ← enter | B33: 1119
A34: Upside / (Downside) to CMP | B34: =IFERROR((B31-B33)/B33,0) -> -0.25644233
A35: Recommendation | B35: =IF(B34>0.15,"BUY",IF(B34<-0.1,"SELL","HOLD")) -> SELL

Sheet Sensitivity
A1: SENSITIVITY ANALYSIS | Intrinsic Value per Share (₹)
A2: Rows = WACC (%) | Columns = Terminal Growth Rate (g %)
A4: WACC \ g | B4: 0.02 | C4: 0.025 | D4: 0.03 | E4: 0.035 | F4: 0.04 | G4: 0.045 | H4: 0.05
A5: 0.07 | B5: =IFERROR(('DCF Model'!B25+('DCF Model'!F13*(1+0.02)/(A5-0.02))/(1+A5)^5-'DCF Model'!B27+'DCF Model'!B28)*100/'DCF Model'!B30,"-") -> 105035.06 | C5: =IFERROR(('DCF Model'!B25+('DCF Model'!F13*(1+0.025)/(A5-0.025))/(1+A5)^5-'DCF Model'!B27+'DCF Model'!B28)*100/'DCF Model'!B30,"-") -> 113684.64 | D5: =IFERROR(('DCF Model'!B25+('DCF Model'!F13*(1+0.03)/(A5-0.03))/(1+A5)^5-'DCF Model'!B27+'DCF Model'!B28)*100/'DCF Model'!B30,"-") -> 124496.61 | E5: =IFERROR(('DCF Model'!B25+('DCF Model'!F13*(1+0.035)/(A5-0.035))/(1+A5)^5-'DCF Model'!B27+'DCF Model'!B28)*100/'DCF Model'!B30,"-") -> 138397.71 | F5: =IFERROR(('DCF Model'!B25+('DCF Model'!F13*(1+0.04)/(A5-0.04))/(1+A5)^5-'DCF Model'!B27+'DCF Model'!B28)*100/'DCF Model'!B30,"-") -> 156932.52 | G5: =IFERROR(('DCF Model'!B25+('DCF Model'!F13*(1+0.045)/(A5-0.045))/(1+A5)^5-'DCF Model'!B27+'DCF Model'!B28)*100/'DCF Model'!B30,"-") -> 182881.26 | H5: =IFERROR(('DCF Model'!B25+('DCF Model'!F13*(1+0.05)/(A5-0.05))/(1+A5)^5-'DCF Model'!B27+'DCF Model'!B28)*100/'DCF Model'!B30,"-") -> 221804.35
A6: 0.075 | B6: =IFERROR(('DCF Model'!B25+('DCF Model'!F13*(1+0.02)/(A6-0.02))/(1+A6)^5-'DCF Model'!B27+'DCF Model'!B28)*100/'DCF Model'!B30,"-") -> 96734.465 | C6: =IFERROR(('DCF Model'!B25+('DCF Model'!F13*(1+0.025)/(A6-0.025))/(1+A6)^5-'DCF Model'!B27+'DCF Model'!B28)*100/'DCF Model'!B30,"-") -> 103680.64 | D6: =IFERROR(('DCF Model'!B25+('DCF Model'!F13*(1+0.03)/(A6-0.03))/(1+A6)^5-'DCF Model'!B27+'DCF Model'!B28)*100/'DCF Model'!B30,"-") -> 112170.42 | E6: =IFERROR(('DCF Model'!B25+('DCF Model'!F13*(1+0.035)/(A6-0.035))/(1+A6)^5-'DCF Model'!B27+'DCF Model'!B28)*100/'DCF Model'!B30,"-") -> 122782.64 | F6: =IFERROR(('DCF Model'!B25+('DCF Model'!F13*(1+0.04)/(A6-0.04))/(1+A6)^5-'DCF Model'!B27+'DCF Model'!B28)*100/'DCF Model'!B30,"-") -> 136426.92 | G6: =IFERROR(('DCF Model'!B25+('DCF Model'!F13*(1+0.045)/(A6-0.045))/(1+A6)^5-'DCF Model'!B27+'DCF Model'!B28)*100/'DCF Model'!B30,"-") -> 154619.29 | H6: =IFERROR(('DCF Model'!B25+('DCF Model'!F13*(1+0.05)/(A6-0.05))/(1+A6)^5-'DCF Model'!B27+'DCF Model'!B28)*100/'DCF Model'!B30,"-") -> 180088.61
A7: 0.08 | B7: =IFERROR(('DCF Model'!B25+('DCF Model'!F13*(1+0.02)/(A7-0.02))/(1+A7)^5-'DCF Model'!B27+'DCF Model'!B28)*100/'DCF Model'!B30,"-") -> 89856.518 | C7: =IFERROR(('DCF Model'!B25+('DCF Model'!F13*(1+0.025)/(A7-0.025))/(1+A7)^5-'DCF Model'!B27+'DCF Model'!B28)*100/'DCF Model'!B30,"-") -> 95538.548 | D7: =IFERROR(('DCF Model'!B25+('DCF Model'!F13*(1+0.03)/(A7-0.03))/(1+A7)^5-'DCF Model'!B27+'DCF Model'!B28)*100/'DCF Model'!B30,"-") -> 102356.98 | E7: =IFERROR(('DCF Model'!B25+('DCF Model'!F13*(1+0.035)/(A7-0.035))/(1+A7)^5-'DCF Model'!B27+'DCF Model'!B28)*100/'DCF Model'!B30,"-") -> 110690.63 | F7: =IFERROR(('DCF Model'!B25+('DCF Model'!F13*(1+0.04)/(A7-0.04))/(1+A7)^5-'DCF Model'!B27+'DCF Model'!B28)*100/'DCF Model'!B30,"-") -> 121107.68 | G7: =IFERROR(('DCF Model'!B25+('DCF Model'!F13*(1+0.045)/(A7-0.045))/(1+A7)^5-'DCF Model'!B27+'DCF Model'!B28)*100/'DCF Model'!B30,"-") -> 134501.04 | H7: =IFERROR(('DCF Model'!B25+('DCF Model'!F13*(1+0.05)/(A7-0.05))/(1+A7)^5-'DCF Model'!B27+'DCF Model'!B28)*100/'DCF Model'!B30,"-") -> 152358.85
A8: 0.085 | B8: =IFERROR(('DCF Model'!B25+('DCF Model'!F13*(1+0.02)/(A8-0.02))/(1+A8)^5-'DCF Model'!B27+'DCF Model'!B28)*100/'DCF Model'!B30,"-") -> 84071.756 | C8: =IFERROR(('DCF Model'!B25+('DCF Model'!F13*(1+0.025)/(A8-0.025))/(1+A8)^5-'DCF Model'!B27+'DCF Model'!B28)*100/'DCF Model'!B30,"-") -> 88791.614 | D8: =IFERROR(('DCF Model'!B25+('DCF Model'!F13*(1+0.03)/(A8-0.03))/(1+A8)^5-'DCF Model'!B27+'DCF Model'!B28)*100/'DCF Model'!B30,"-") -> 94369.629 | E8: =IFERROR(('DCF Model'!B25+('DCF Model'!F13*(1+0.035)/(A8-0.035))/(1+A8)^5-'DCF Model'!B27+'DCF Model'!B28)*100/'DCF Model'!B30,"-") -> 101063.25 | F8: =IFERROR(('DCF Model'!B25+('DCF Model'!F13*(1+0.04)/(A8-0.04))/(1+A8)^5-'DCF Model'!B27+'DCF Model'!B28)*100/'DCF Model'!B30,"-") -> 109244.33 | G8: =IFERROR(('DCF Model'!B25+('DCF Model'!F13*(1+0.045)/(A8-0.045))/(1+A8)^5-'DCF Model'!B27+'DCF Model'!B28)*100/'DCF Model'!B30,"-") -> 119470.69 | H8: =IFERROR(('DCF Model'!B25+('DCF Model'!F13*(1+0.05)/(A8-0.05))/(1+A8)^5-'DCF Model'!B27+'DCF Model'!B28)*100/'DCF Model'!B30,"-") -> 132618.87
A9: 0.09 | B9: =IFERROR(('DCF Model'!B25+('DCF Model'!F13*(1+0.02)/(A9-0.02))/(1+A9)^5-'DCF Model'!B27+'DCF Model'!B28)*100/'DCF Model'!B30,"-") -> 79144.891 | C9: =IFERROR(('DCF Model'!B25+('DCF Model'!F13*(1+0.025)/(A9-0.025))/(1+A9)^5-'DCF Model'!B27+'DCF Model'!B28)*100/'DCF Model'!B30,"-") -> 83116.762 | D9: =IFERROR(('DCF Model'!B25+('DCF Model'!F13*(1+0.03)/(A9-0.03))/(1+A9)^5-'DCF Model'!B27+'DCF Model'!B28)*100/'DCF Model'!B30,"-") -> 87750.612 | E9: =IFERROR(('DCF Model'!B25+('DCF Model'!F13*(1+0.035)/(A9-0.035))/(1+A9)^5-'DCF Model'!B27+'DCF Model'!B28)*100/'DCF Model'!B30,"-") -> 93226.979 | F9: =IFERROR(('DCF Model'!B25+('DCF Model'!F13*(1+0.04)/(A9-0.04))/(1+A9)^5-'DCF Model'!B27+'DCF Model'!B28)*100/'DCF Model'!B30,"-") -> 99798.62 | G9: =IFERROR(('DCF Model'!B25+('DCF Model'!F13*(1+0.045)/(A9-0.045))/(1+A9)^5-'DCF Model'!B27+'DCF Model'!B28)*100/'DCF Model'!B30,"-") -> 107830.63 | H9: =IFERROR(('DCF Model'!B25+('DCF Model'!F13*(1+0.05)/(A9-0.05))/(1+A9)^5-'DCF Model'!B27+'DCF Model'!B28)*100/'DCF Model'!B30,"-") -> 117870.63
A10: 0.095 | B10: =IFERROR(('DCF Model'!B25+('DCF Model'!F13*(1+0.02)/(A10-0.02))/(1+A10)^5-'DCF Model'!B27+'DCF Model'!B28)*100/'DCF Model'!B30,"-") -> 74903.413 | C10: =IFERROR(('DCF Model'!B25+('DCF Model'!F13*(1+0.025)/(A10-0.025))/(1+A10)^5-'DCF Model'!B27+'DCF Model'!B28)*100/'DCF Model'!B30,"-") -> 78283.257 | D10: =IFERROR(('DCF Model'!B25+('DCF Model'!F13*(1+0.03)/(A10-0.03))/(1+A10)^5-'DCF Model'!B27+'DCF Model'!B28)*100/'DCF Model'!B30,"-") -> 82183.078 | E10: =IFERROR(('DCF Model'!B25+('DCF Model'!F13*(1+0.035)/(A10-0.035))/(1+A10)^5-'DCF Model'!B27+'DCF Model'!B28)*100/'DCF Model'!B30,"-") -> 86732.869 | F10: =IFERROR(('DCF Model'!B25+('DCF Model'!F13*(1+0.04)/(A10-0.04))/(1+A10)^5-'DCF Model'!B27+'DCF Model'!B28)*100/'DCF Model'!B30,"-") -> 92109.894 | G10: =IFERROR(('DCF Model'!B25+('DCF Model'!F13*(1+0.045)/(A10-0.045))/(1+A10)^5-'DCF Model'!B27+'DCF Model'!B28)*100/'DCF Model'!B30,"-") -> 98562.325 | H10: =IFERROR(('DCF Model'!B25+('DCF Model'!F13*(1+0.05)/(A10-0.05))/(1+A10)^5-'DCF Model'!B27+'DCF Model'!B28)*100/'DCF Model'!B30,"-") -> 106448.63
A11: 0.1 | B11: =IFERROR(('DCF Model'!B25+('DCF Model'!F13*(1+0.02)/(A11-0.02))/(1+A11)^5-'DCF Model'!B27+'DCF Model'!B28)*100/'DCF Model'!B30,"-") -> 71217.969 | C11: =IFERROR(('DCF Model'!B25+('DCF Model'!F13*(1+0.025)/(A11-0.025))/(1+A11)^5-'DCF Model'!B27+'DCF Model'!B28)*100/'DCF Model'!B30,"-") -> 74121.928 | D11: =IFERROR(('DCF Model'!B25+('DCF Model'!F13*(1+0.03)/(A11-0.03))/(1+A11)^5-'DCF Model'!B27+'DCF Model'!B28)*100/'DCF Model'!B30,"-") -> 77440.739 | E11: =IFERROR(('DCF Model'!B25+('DCF Model'!F13*(1+0.035)/(A11-0.035))/(1+A11)^5-'DCF Model'!B27+'DCF Model'!B28)*100/'DCF Model'!B30,"-") -> 81270.135 | F11: =IFERROR(('DCF Model'!B25+('DCF Model'!F13*(1+0.04)/(A11-0.04))/(1+A11)^5-'DCF Model'!B27+'DCF Model'!B28)*100/'DCF Model'!B30,"-") -> 85737.765 | G11: =IFERROR(('DCF Model'!B25+('DCF Model'!F13*(1+0.045)/(A11-0.045))/(1+A11)^5-'DCF Model'!B27+'DCF Model'!B28)*100/'DCF Model'!B30,"-") -> 91017.691 | H11: =IFERROR(('DCF Model'!B25+('DCF Model'!F13*(1+0.05)/(A11-0.05))/(1+A11)^5-'DCF Model'!B27+'DCF Model'!B28)*100/'DCF Model'!B30,"-") -> 97353.602

Sheet Investment Thesis
A1: INVESTMENT THESIS | NATCO PHARMA LTD (NSE: NATCOPHARM)
A3: Company Overview | B3: Natco Pharma Ltd is a vertically integrated, R&D-focused pharma company based in Hyderabad. It operates across Export Formulations (US, Canada, EU), Domestic Formulations (oncology, hepatitis, crop health sciences), and APIs. Natco is known for Para IV first-to-file filings in the US and has been a key beneficiary of Lenalidomide (Revlimid) generic exclusivity since FY23. Market Cap: ~₹20,042 Cr | Shares: ~17.9 Cr | Face Value: ₹2.
A4: Investment Thesis | B4: Natco openly describes itself as a 'jackpot chaser' — it deliberately targets high-risk, high-reward generic molecules. The FY23–FY25 earnings boom was driven by Lenalidomide (blockbuster cancer drug), which gave it limited-competition exclusivity in the US. Beyond Revlimid, Natco has a deep pipeline of Para IV filings, oncology APIs, and is scaling crop health sciences. Its moat: deep R&D capability, first-to-file IP expertise, and net-zero debt with ~₹3,500 Cr cash war chest for M&A.
A5: Revenue & Margin Outlook | B5: FY25 was peak earnings (Revenue ₹4,430 Cr, EBITDA ₹2,196 Cr, PAT ₹1,883 Cr, margin 50%). FY26 onwards, Lenalidomide exclusivity fades as more generics enter → revenues expected to decline ~15-17% in FY26. Recovery driven by: (1) new Para IV launches in US, (2) domestic oncology ramp-up, (3) crop health sciences growth, (4) API exports. Conservative assumption: normalised EBITDA margin of 28–34% post-Revlimid, recovering as new products scale.
A6: Key Risks | B6: 1. Revlimid cliff: FY26–27 earnings will compress sharply as Lenalidomide competition intensifies — this is the single biggest near-term risk. 2. USFDA regulatory risk: Kothur site is under remediation; any import alert would severely impact US revenues. 3. Pipeline execution risk: Para IV wins are lumpy and unpredictable by nature. 4. Concentration risk: top product/molecule contributes disproportionate revenue. 5. Currency risk: ~60% revenues in USD; INR appreciation hurts.
A7: Valuation Summary | B7: Intrinsic Value: ₹___ (computed by model) | CMP: ₹1,119 | Mkt Cap: ₹20,042 Cr | P/E: 12.8x (FY25) | Book Value: ₹483 | ROCE: 32.8% | ROE: 28% | Debt: ₹279 Cr (near debt-free) | Cash: ~₹3,500 Cr
A8: Comparable Companies | B8: Peers: Sun Pharma (~28x P/E), Dr. Reddy's (~18x), Cipla (~22x), Aurobindo (~12x). Natco at 12.8x P/E (FY25 earnings) looks cheap, but FY25 was a peak year. On normalised FY27E earnings (PAT ~₹850–950 Cr), the P/E re-rates to ~21–23x — in line with peers. EV/EBITDA on normalised basis: ~15x, fair for quality pharma.
A9: Conclusion | B9: Natco is a high-quality compounder with episodic earnings spikes. The Revlimid windfall (FY23–FY25) has been exceptional; the next 2 years will see normalisation. Long-term, the pipeline of Para IV filings and domestic oncology franchise supports 12–15% EPS CAGR post-FY27. BUY only if the DCF model shows >15% upside on conservative (normalised) assumptions. The large cash balance (₹3,500 Cr) provides significant downside protection and optionality for acquisitions.
